tracegroomer/__init__.py
tracegroomer/__main__.py
tracegroomer/tests/__init__.py
tracegroomer/tests/test_tidy.py
tracegroomer/tests/test_utils.py
tracegroomer/tidy.py
tracegroomer/utils.py
tracegroomer-0.1.4.dist-info/LICENSE
tracegroomer-0.1.4.dist-info/METADATA
tracegroomer-0.1.4.dist-info/WHEEL
tracegroomer-0.1.4.dist-info/entry_points.txt
tracegroomer-0.1.4.dist-info/RECORD
