Metadata-Version: 2.1
Name: tracegroomer
Version: 0.1.4
Summary: Convert and normalise metabolomics data formats (preprocessing for DIMet)
Home-page: https://github.com/cbib/TraceGroomer.git
License: MIT
Author: Johanna Galvis Rodriguez
Author-email: deisy-johanna.galvis-rodriguez@u-bordeaux.fr
Maintainer: Benjamin Dartigues
Maintainer-email: benjamin.dartigues@u-bordeaux.fr
Requires-Python: >=3.10,<4.0
Classifier: License :: OSI Approved :: MIT License
Classifier: Programming Language :: Python :: 3
Classifier: Programming Language :: Python :: 3.10
Classifier: Programming Language :: Python :: 3.11
Classifier: Programming Language :: Python :: 3.12
Requires-Dist: PyYAML (>=6.0.1,<7.0.0)
Requires-Dist: Sphinx (>=7.2.6,<8.0.0)
Requires-Dist: click (>=8.1.7,<9.0.0)
Requires-Dist: matplotlib (>=3.8.2,<4.0.0)
Requires-Dist: mypy (>=1.8.0,<2.0.0)
Requires-Dist: numpy (>=1.26.4,<2.0.0)
Requires-Dist: openpyxl (>=3.1.2,<4.0.0)
Requires-Dist: pandas (>=2.2.0,<3.0.0)
Requires-Dist: pydantic (>=1.10.8,<2.0.0)
Requires-Dist: python-dotenv (>=1.0.1,<2.0.0)
Requires-Dist: scikit-learn (>=1.4.0,<2.0.0)
Requires-Dist: scipy (>=1.12.0,<2.0.0)
Requires-Dist: seaborn (>=0.13.2,<0.14.0)
Project-URL: Repository, https://github.com/cbib/TraceGroomer.git
